custos/__init__.py
custos/_wrap.py
custos/apps.py
custos/auto.py
custos/autocapture.py
custos/bootstrap.py
custos/client.py
custos/config.py
custos/custos_test.py
custos/decorators.py
custos/ethics.py
custos/exceptions.py
custos/guardian.py
custos/middleware.py
custos/models.py
custos/monitor.py
custos/policy.py
custos/registry.py
custos/tasks.py
custos/training.py
custos/utils.py
custos/validation.py
custos/integrations/__init__.py
custos/integrations/django.py
custos/migrations/0001_initial.py
custos/migrations/__init__.py
custos_labs-0.2.5.dist-info/licenses/LICENSE
custos_labs-0.2.5.dist-info/METADATA
custos_labs-0.2.5.dist-info/WHEEL
custos_labs-0.2.5.dist-info/top_level.txt
custos_labs-0.2.5.dist-info/RECORD
