Metadata-Version: 2.4
Name: custos-labs
Version: 0.2.5
Summary: Custos – The AI Alignment Guardian. Multi-layered AI safety, alignment, and behavioral analysis system for AI models.
Home-page: https://github.com/dev-77-sys
Author: Sylvester Duah
Author-email: Sylvester Duah <dev@custoslabs.com>
License-Expression: MIT
Project-URL: Homepage, https://custoslabs.com/
Project-URL: Documentation, https://custoslabs.com/documentation
Project-URL: Source, https://github.com/dev-77-sys/custos-labs
Project-URL: BugTracker, https://github.com/dev-77-sys/custos-labs/issues
Keywords: ai-alignment,AGI,AI safety,LLM,machine learning,ethics,alignment,AI monitoring,AI Violations,Compliances
Classifier: Programming Language :: Python :: 3
Classifier: Programming Language :: Python :: 3.8
Classifier: Programming Language :: Python :: 3.9
Classifier: Programming Language :: Python :: 3.10
Classifier: Programming Language :: Python :: 3.11
Classifier: Operating System :: OS Independent
Classifier: Topic :: Software Development :: Libraries
Classifier: Intended Audience :: Developers
Classifier: Intended Audience :: Science/Research
Requires-Python: >=3.8
License-File: LICENSE
Requires-Dist: requests>=2.31.0
Dynamic: author
Dynamic: home-page
Dynamic: license-file
Dynamic: requires-python
